task_terminal-0.1.1.dist-info/licenses/LICENSE
tt/__init__.py
tt/main.py
tt/core/__init__.py
tt/core/ids.py
tt/core/tasks.py
tt/infra/__init__.py
tt/infra/github.py
tt/infra/sqlite.py
tt/tui/__init__.py
tt/tui/app.py
tt/tui/screens/__init__.py
tt/tui/screens/create_task.py
tt/tui/screens/menu.py
tt/tui/screens/pr_inbox.py
tt/tui/screens/tasks.py
task_terminal-0.1.1.dist-info/METADATA
task_terminal-0.1.1.dist-info/WHEEL
task_terminal-0.1.1.dist-info/entry_points.txt
task_terminal-0.1.1.dist-info/top_level.txt
task_terminal-0.1.1.dist-info/RECORD
