Metadata-Version: 2.4
Name: task-terminal
Version: 0.1.1
Summary: Task Terminal - A local-first developer tool for generating and tracking task IDs
Author: Sumantha K A
Requires-Python: >=3.9
License-File: LICENSE
Requires-Dist: textual>=0.47.0
Requires-Dist: rich>=13.7.0
Requires-Dist: pyperclip>=1.8.2
Requires-Dist: ruff>=0.14.10
Provides-Extra: dev
Requires-Dist: pytest>=7.4.0; extra == "dev"
Requires-Dist: pytest-asyncio>=0.21.0; extra == "dev"
Dynamic: license-file
